ankirobo/__init__.py
ankirobo/api.py
ankirobo/input.py
ankirobo/output.py
ankirobo/types.py
ankirobo/cli/args.py
ankirobo/cli/main.py
ankirobo/cli/ops.py
ankirobo/extractors/__init__.py
ankirobo/extractors/all.py
ankirobo/extractors/jotoba.py
ankirobo/extractors/helpers/api.py
ankirobo/extractors/helpers/web.py
ankirobo/extractors/linguee/shared.py
ankirobo/extractors/testdata/__init__.py
ankirobo/extractors/testdata/jotoba/あるきまわる.json
ankirobo/extractors/testdata/jotoba/はちどり.json
ankirobo/extractors/testdata/jotoba/ぴかぴか.json
ankirobo/extractors/testdata/jotoba/嵐.json
ankirobo/extractors/testdata/linguee/french_english/encre.html
ankirobo/extractors/testdata/linguee/french_english/flâner.html
ankirobo/extractors/testdata/linguee/french_english/hilarant.html
ankirobo/extractors/testdata/linguee/french_english/mettre en valeur.html
ankirobo/extractors/testdata/linguee/french_english/oreiller.html
ankirobo/extractors/testdata/linguee/french_english/pas de soucis.html
ankirobo/extractors/testdata/linguee/french_english/pister.html
ankirobo/extractors/testdata/linguee/french_english/tonnerre.html
ankirobo/extractors/testdata/linguee/french_english/à succès.html
ankirobo/extractors/testdata/linguee/french_english/écrouler.html
ankirobo/extractors/testdata/linguee/german_english/schiff.html
ankirobo/extractors/testdata/linguee/german_english/sorgfältig.html
ankirobo/extractors/testdata/linguee/german_english/suchen.html
ankirobo/extractors/testdata/linguee/spanish_english/calavera.html
ankirobo/extractors/testdata/linguee/spanish_english/perseguir.html
ankirobo/extractors/testdata/linguee/spanish_english/suscribirse.html
ankirobo/extractors/testdata/linguee/spanish_english/tormenta.html
ankirobo/extractors/testdata/linguee/spanish_english/videojuego.html
anki_robo-0.1.0.dist-info/METADATA
anki_robo-0.1.0.dist-info/WHEEL
anki_robo-0.1.0.dist-info/entry_points.txt
anki_robo-0.1.0.dist-info/licenses/LICENSE
anki_robo-0.1.0.dist-info/RECORD
