Metadata-Version: 2.3
Name: anki-robo
Version: 0.1.0
Summary: An Anki-card-creation framework
Project-URL: GitHub, https://github.com/keithfancher/anki-robo
Author: Keith Fancher
License-File: LICENSE
Keywords: anki
Classifier: Development Status :: 4 - Beta
Classifier: License :: OSI Approved :: GNU General Public License v3 (GPLv3)
Classifier: Operating System :: OS Independent
Classifier: Programming Language :: Python :: 3
Requires-Python: >=3.9
Requires-Dist: beautifulsoup4
Requires-Dist: requests
